[
    {        
        "name":"Main Header",
        "title_text":"Lorem & Ipsum",
        "subtitle_text":"",
        "content_text":"<h4>TypeB Content<br><\/h4>",
        "comment_text":"TypeB Comment",
        "type":"typeB",
        "click_url":"local\/menus",
        "element_image":"\/specials.jpg",
        "element_images":null,
        "element_images_info":"a:0:{}",
        "button_status":"1",
        "button_text":"order now!",
        "steps":"a:0:{}",
        "steps_background":"#112113",
        "status":"1"
    },
    {        
        "name":"Categories Name",
        "title_text":"Categories Title",
        "subtitle_text":"",
        "content_text":"",
        "comment_text":"Categories Comment",
        "type":"typeC",
        "click_url":"",
        "element_image":null,
        "element_images":null,
        "element_images_info":"a:0:{}",
        "button_status":"0",
        "button_text":"",
        "steps":null,
        "steps_background":null,
        "status":"1"
    },
    {        
        "name":"Featured Name",
        "title_text":"Featured Title",
        "subtitle_text":"",
        "content_text":"",
        "comment_text":"Featured Comment",
        "type":"typeD",
        "click_url":"",
        "element_image":null,
        "element_images":null,
        "element_images_info":"a:0:{}",
        "button_status":"0",
        "button_text":"",
        "steps":null,
        "steps_background":null,
        "status":"1"
    },
    {        
        "name":"Steps Name",
        "title_text":"Lorem ipsum dolor sit amet",
        "subtitle_text":"",
        "content_text":"",
        "comment_text":"consectetur adipiscing elit",
        "type":"typeE",
        "click_url":"",
        "element_image":null,
        "element_images":null,
        "element_images_info":"a:0:{}",
        "button_status":"0",
        "button_text":"",
        "steps":"a:3:{i:1;a:3:{s:5:\"title\";s:11:\"Lorem ipsum\";s:8:\"subTitle\";s:58:\"Ut enim ad minim veniam, quis nostrud exercitation ullamco\";s:4:\"icon\";s:10:\"ti-map-alt\";}i:2;a:3:{s:5:\"title\";s:11:\"Lorem ipsum\";s:8:\"subTitle\";s:58:\"Ut enim ad minim veniam, quis nostrud exercitation ullamco\";s:4:\"icon\";s:7:\"ti-time\";}i:3;a:3:{s:5:\"title\";s:11:\"Lorem ipsum\";s:8:\"subTitle\";s:58:\"Ut enim ad minim veniam, quis nostrud exercitation ullamco\";s:4:\"icon\";s:14:\"ti-credit-card\";}}",
        "steps_background":"#112113",
        "status":"1"
    }
]
